easydstools/__init__.py
easydstools-0.0.1.dist-info/LICENSE
easydstools-0.0.1.dist-info/METADATA
easydstools-0.0.1.dist-info/WHEEL
easydstools-0.0.1.dist-info/top_level.txt
easydstools-0.0.1.dist-info/RECORD
