Metadata-Version: 2.1
Name: easydstools
Version: 0.0.1
Summary: Data Science toolkit I use a lot
Home-page: https://github.com/celmore25/clay-ds/
Author: Clay Elmore
Author-email: celmore25@gmail.com
License: Apache 2.0
Platform: UNKNOWN
